mc_diag_boat/__init__.py
mc_diag_boat/angle.py
mc_diag_boat/formatting.py
mc_diag_boat/input.py
mc_diag_boat/optimization.py
mc_diag_boat/pattern.py
mc_diag_boat/schematic.py
mc_diag_boat/vec2.py
mc_diag_boat-0.3.0.dist-info/LICENSE
mc_diag_boat-0.3.0.dist-info/METADATA
mc_diag_boat-0.3.0.dist-info/WHEEL
mc_diag_boat-0.3.0.dist-info/RECORD
