Metadata-Version: 2.3
Name: mc_diag_boat
Version: 0.3.0
Summary: A set of functions for building diagonal boat roads in Minecraft
License: GPL-3.0-or-later
Author: Ribqah
Requires-Python: >=3.11,<4.0
Classifier: License :: OSI Approved :: GNU General Public License v3 or later (GPLv3+)
Classifier: Programming Language :: Python :: 3
Classifier: Programming Language :: Python :: 3.11
Classifier: Programming Language :: Python :: 3.12
Classifier: Programming Language :: Python :: 3.13
Requires-Dist: litemapy (>=0.10.0b0,<0.11.0)
Requires-Dist: matplotlib (>=3.10.0,<4.0.0)
Requires-Dist: numpy (>=2.0.0,<3.0.0)
Requires-Dist: scikit-image (>=0.25.0,<0.26.0)
Project-URL: Repository, https://github.com/ribqahisabsent/mc-diag-boat.git
